apple_hdr_heic/__init__.py
apple_hdr_heic/decoder.py
apple_hdr_heic/lib.py
apple_hdr_heic/metadata.py
apple_hdr_heic/py.typed
apple_hdr_heic-0.1.0.dist-info/entry_points.txt
apple_hdr_heic-0.1.0.dist-info/LICENSE
apple_hdr_heic-0.1.0.dist-info/WHEEL
apple_hdr_heic-0.1.0.dist-info/METADATA
apple_hdr_heic-0.1.0.dist-info/RECORD
