Metadata-Version: 2.3
Name: apple-hdr-heic
Version: 0.1.0
Summary: A library/tool to decode images in HEIC/HEIF format taken on Apple devices that contain HDR gain map.
Keywords: heic,heif,converter,decoder,HDR,HDR Gain Map,iPhone,EXR
Author-email: John Charankattu <john.ch.fr@gmail.com>
Requires-Python: >=3.10
Classifier: Development Status :: 3 - Alpha
Classifier: Programming Language :: Python :: 3
Classifier: License :: OSI Approved :: MIT License
Classifier: Operating System :: OS Independent
Classifier: Topic :: Multimedia :: Graphics
Classifier: Topic :: Multimedia :: Graphics :: Graphics Conversion
Requires-Dist: colour-science>=0.4.5
Requires-Dist: numpy>=1.24.0
Requires-Dist: opencv-python-headless>=4.0
Requires-Dist: openexr>=3.3.2,<4.0
Requires-Dist: pillow_heif>=0.20.0
Requires-Dist: PyExifTool>=0.5.6
Project-URL: Homepage, https://github.com/johncf/apple-hdr-heic
